{
  "annotations": {"list":[]},
  "description": "Are messages flowing without loss? Where is the pipeline backing up?",
  "editable": true,
  "graphTooltip": 1,
  "links": [{"title":"Sukko Dashboards","type":"dashboards","tags":["sukko"],"includeVars":true,"keepTime":true,"icon":"external link"}],
  "panels": [
    {"type":"row","id":1,"title":"Pipeline Flow","gridPos":{"h":1,"w":24,"x":0,"y":0},"collapsed":false,"panels":[]},
    {"type":"stat","id":2,"title":"Kafka Ingested/s","gridPos":{"h":3,"w":6,"x":0,"y":1},"datasource":{"type":"prometheus","uid":"${datasource}"},"fieldConfig":{"defaults":{"color":{"mode":"fixed","fixedColor":"#5794F2"},"unit":"ops","thresholds":{"mode":"absolute","steps":[{"color":"blue","value":null}]}}},"options":{"colorMode":"none","graphMode":"area","justifyMode":"center","reduceOptions":{"calcs":["lastNotNull"]},"textMode":"auto","orientation":"auto"},"targets":[{"datasource":{"type":"prometheus","uid":"${datasource}"},"expr":"sum(rate(ws_kafka_messages_received_total[1m]))","legendFormat":""}]},
    {"type":"stat","id":3,"title":"Gateway Proxied/s","gridPos":{"h":3,"w":6,"x":6,"y":1},"datasource":{"type":"prometheus","uid":"${datasource}"},"fieldConfig":{"defaults":{"color":{"mode":"fixed","fixedColor":"#5794F2"},"unit":"ops","thresholds":{"mode":"absolute","steps":[{"color":"blue","value":null}]}}},"options":{"colorMode":"none","graphMode":"area","justifyMode":"center","reduceOptions":{"calcs":["lastNotNull"]},"textMode":"auto","orientation":"auto"},"targets":[{"datasource":{"type":"prometheus","uid":"${datasource}"},"expr":"sum(rate(gateway_messages_total{direction=\"upstream\"}[1m]))","legendFormat":""}]},
    {"type":"stat","id":4,"title":"Delivered/s","gridPos":{"h":3,"w":6,"x":12,"y":1},"datasource":{"type":"prometheus","uid":"${datasource}"},"fieldConfig":{"defaults":{"color":{"mode":"fixed","fixedColor":"#73BF69"},"unit":"ops","thresholds":{"mode":"absolute","steps":[{"color":"green","value":null}]}}},"options":{"colorMode":"none","graphMode":"area","justifyMode":"center","reduceOptions":{"calcs":["lastNotNull"]},"textMode":"auto","orientation":"auto"},"targets":[{"datasource":{"type":"prometheus","uid":"${datasource}"},"expr":"sum(rate(ws_messages_sent_total[1m]))","legendFormat":""}]},
    {"type":"stat","id":5,"title":"Dropped/s","gridPos":{"h":3,"w":6,"x":18,"y":1},"datasource":{"type":"prometheus","uid":"${datasource}"},"fieldConfig":{"defaults":{"color":{"mode":"thresholds"},"unit":"ops","thresholds":{"mode":"absolute","steps":[{"color":"green","value":null},{"color":"yellow","value":1},{"color":"red","value":10}]}}},"options":{"colorMode":"background","graphMode":"area","justifyMode":"center","reduceOptions":{"calcs":["lastNotNull"]},"textMode":"auto","orientation":"auto"},"targets":[{"datasource":{"type":"prometheus","uid":"${datasource}"},"expr":"sum(rate(ws_dropped_broadcasts_detailed_total[1m]))","legendFormat":""}]},
    {"type":"row","id":6,"title":"End-to-End Throughput","gridPos":{"h":1,"w":24,"x":0,"y":4},"collapsed":false,"panels":[]},
    {"type":"timeseries","id":7,"title":"End-to-End Message Flow","gridPos":{"h":8,"w":24,"x":0,"y":5},"datasource":{"type":"prometheus","uid":"${datasource}"},"fieldConfig":{"defaults":{"custom":{"lineInterpolation":"smooth","fillOpacity":10,"showPoints":"never","spanNulls":true}},"overrides":[{"matcher":{"id":"byName","options":"Kafka Consumed/s"},"properties":[{"id":"color","value":{"fixedColor":"#5794F2","mode":"fixed"}}]},{"matcher":{"id":"byName","options":"Broadcast/s"},"properties":[{"id":"color","value":{"fixedColor":"#B877D9","mode":"fixed"}}]},{"matcher":{"id":"byName","options":"WS Delivered/s"},"properties":[{"id":"color","value":{"fixedColor":"#73BF69","mode":"fixed"}}]},{"matcher":{"id":"byName","options":"Dropped/s"},"properties":[{"id":"color","value":{"fixedColor":"#F2495C","mode":"fixed"}}]}]},"options":{"tooltip":{"mode":"multi","sort":"desc"},"legend":{"displayMode":"table","placement":"bottom","calcs":["mean","max","last"]}},"targets":[{"datasource":{"type":"prometheus","uid":"${datasource}"},"expr":"sum(rate(ws_kafka_messages_received_total[1m]))","legendFormat":"Kafka Consumed/s"},{"datasource":{"type":"prometheus","uid":"${datasource}"},"expr":"sum(rate(ws_backend_messages_published_total[1m]))","legendFormat":"Broadcast/s"},{"datasource":{"type":"prometheus","uid":"${datasource}"},"expr":"sum(rate(ws_messages_sent_total[1m]))","legendFormat":"WS Delivered/s"},{"datasource":{"type":"prometheus","uid":"${datasource}"},"expr":"sum(rate(ws_dropped_broadcasts_detailed_total[1m]))","legendFormat":"Dropped/s"}]},
    {"type":"row","id":8,"title":"Kafka Consumer Lag","gridPos":{"h":1,"w":24,"x":0,"y":13},"collapsed":false,"panels":[]},
    {"type":"timeseries","id":9,"title":"Consumer Lag by Group","gridPos":{"h":8,"w":16,"x":0,"y":14},"datasource":{"type":"prometheus","uid":"${datasource}"},"fieldConfig":{"defaults":{"custom":{"lineInterpolation":"smooth","fillOpacity":5,"showPoints":"never","thresholdsStyle":{"mode":"line"}}},"defaults":{"thresholds":{"mode":"absolute","steps":[{"color":"green","value":null},{"color":"yellow","value":100},{"color":"red","value":1000}]}}},"options":{"tooltip":{"mode":"multi"},"legend":{"displayMode":"table","placement":"bottom","calcs":["mean","max","last"]}},"targets":[{"datasource":{"type":"prometheus","uid":"${datasource}"},"expr":"max by (topic,consumer_group) (ws_kafka_consumer_lag)","legendFormat":"{{topic}} / {{consumer_group}}"}]},
    {"type":"stat","id":10,"title":"Max Consumer Lag","gridPos":{"h":8,"w":8,"x":16,"y":14},"datasource":{"type":"prometheus","uid":"${datasource}"},"fieldConfig":{"defaults":{"color":{"mode":"thresholds"},"thresholds":{"mode":"absolute","steps":[{"color":"green","value":null},{"color":"yellow","value":100},{"color":"red","value":1000}]}}},"options":{"colorMode":"background","graphMode":"area","justifyMode":"center","reduceOptions":{"calcs":["lastNotNull"]},"textMode":"auto","orientation":"auto"},"targets":[{"datasource":{"type":"prometheus","uid":"${datasource}"},"expr":"max(ws_kafka_consumer_lag) or vector(0)","legendFormat":""}]},
    {"type":"row","id":11,"title":"Drop Analysis","gridPos":{"h":1,"w":24,"x":0,"y":22},"collapsed":false,"panels":[]},
    {"type":"piechart","id":12,"title":"Drop Reasons","gridPos":{"h":8,"w":12,"x":0,"y":23},"datasource":{"type":"prometheus","uid":"${datasource}"},"fieldConfig":{"defaults":{"color":{"mode":"palette-classic"}}},"options":{"pieType":"pie","legend":{"displayMode":"table","placement":"right","values":["value","percent"]},"tooltip":{"mode":"multi"}},"targets":[{"datasource":{"type":"prometheus","uid":"${datasource}"},"expr":"sum by (reason) (rate(ws_dropped_broadcasts_detailed_total[5m]))","legendFormat":"{{reason}}"}]},
    {"type":"timeseries","id":13,"title":"Drop Trend by Reason","gridPos":{"h":8,"w":12,"x":12,"y":23},"datasource":{"type":"prometheus","uid":"${datasource}"},"fieldConfig":{"defaults":{"custom":{"lineInterpolation":"smooth","stacking":{"mode":"normal"},"fillOpacity":70,"showPoints":"never"}}},"options":{"tooltip":{"mode":"multi"},"legend":{"displayMode":"table","placement":"bottom","calcs":["sum"]}},"targets":[{"datasource":{"type":"prometheus","uid":"${datasource}"},"expr":"sum by (reason) (rate(ws_dropped_broadcasts_detailed_total[5m]))","legendFormat":"{{reason}}"}]},
    {"type":"row","id":14,"title":"Backend Health","gridPos":{"h":1,"w":24,"x":0,"y":31},"collapsed":false,"panels":[]},
    {"type":"stat","id":15,"title":"Kafka Consumer","gridPos":{"h":3,"w":8,"x":0,"y":32},"datasource":{"type":"prometheus","uid":"${datasource}"},"fieldConfig":{"defaults":{"color":{"mode":"thresholds"},"thresholds":{"mode":"absolute","steps":[{"color":"red","value":null},{"color":"green","value":1}]},"mappings":[{"type":"value","options":{"0":{"text":"DOWN","color":"red","index":0},"1":{"text":"UP","color":"green","index":1}}}]}},"options":{"colorMode":"background","graphMode":"none","justifyMode":"center","reduceOptions":{"calcs":["lastNotNull"]},"textMode":"auto","orientation":"auto"},"targets":[{"datasource":{"type":"prometheus","uid":"${datasource}"},"expr":"ws_kafka_connected","instant":true,"legendFormat":""}]},
    {"type":"stat","id":16,"title":"Valkey Broadcast","gridPos":{"h":3,"w":8,"x":8,"y":32},"datasource":{"type":"prometheus","uid":"${datasource}"},"fieldConfig":{"defaults":{"color":{"mode":"thresholds"},"thresholds":{"mode":"absolute","steps":[{"color":"red","value":null},{"color":"green","value":1}]},"mappings":[{"type":"value","options":{"0":{"text":"DOWN","color":"red","index":0},"1":{"text":"UP","color":"green","index":1}}}]}},"options":{"colorMode":"background","graphMode":"none","justifyMode":"center","reduceOptions":{"calcs":["lastNotNull"]},"textMode":"auto","orientation":"auto"},"targets":[{"datasource":{"type":"prometheus","uid":"${datasource}"},"expr":"ws_backend_healthy{backend=\"valkey\"} or vector(0)","instant":true,"legendFormat":""}]},
    {"type":"stat","id":17,"title":"Kafka Backend","gridPos":{"h":3,"w":8,"x":16,"y":32},"datasource":{"type":"prometheus","uid":"${datasource}"},"fieldConfig":{"defaults":{"color":{"mode":"thresholds"},"thresholds":{"mode":"absolute","steps":[{"color":"red","value":null},{"color":"green","value":1}]},"mappings":[{"type":"value","options":{"0":{"text":"DOWN","color":"red","index":0},"1":{"text":"UP","color":"green","index":1}}}]}},"options":{"colorMode":"background","graphMode":"none","justifyMode":"center","reduceOptions":{"calcs":["lastNotNull"]},"textMode":"auto","orientation":"auto"},"targets":[{"datasource":{"type":"prometheus","uid":"${datasource}"},"expr":"ws_backend_healthy{backend=\"kafka\"} or vector(0)","instant":true,"legendFormat":""}]},
    {"type":"row","id":18,"title":"Logs","gridPos":{"h":1,"w":24,"x":0,"y":35},"collapsed":false,"panels":[]},
    {"type":"logs","id":19,"title":"Pipeline Errors & Warnings","gridPos":{"h":10,"w":24,"x":0,"y":36},"datasource":{"type":"loki","uid":"${loki_datasource}"},"options":{"dedupStrategy":"none","enableLogDetails":true,"prettifyLogMessage":false,"showLabels":true,"showTime":true,"sortOrder":"Descending","wrapLogMessage":true},"targets":[{"datasource":{"type":"loki","uid":"${loki_datasource}"},"expr":"{app=~\"ws-server|ws-gateway\",namespace=\"${namespace}\"} | json | level=~\"error|warn\"","legendFormat":""}]}
  ],
  "refresh": "30s",
  "schemaVersion": 39,
  "style": "dark",
  "tags": ["sukko","pipeline"],
  "templating": {
    "list": [
      {"name":"datasource","type":"datasource","query":"prometheus","label":"Prometheus","hide":0,"refresh":1},
      {"name":"loki_datasource","type":"datasource","query":"loki","label":"Loki","hide":0,"refresh":1},
      {"name":"namespace","type":"query","datasource":{"type":"loki","uid":"${loki_datasource}"},"query":"label_values({namespace=~\"sukko.*\"},namespace)","label":"Namespace","hide":0,"refresh":2,"sort":1,"current":{"text":"sukko-demo","value":"sukko-demo"},"includeAll":false,"multi":false}
    ]
  },
  "time": {"from":"now-1h","to":"now"},
  "timepicker": {},
  "timezone": "browser",
  "title": "Sukko — Message Pipeline",
  "uid": "sukko-pipeline",
  "version": 1
}
